calclator.py
MrCalclator-0.0.1.dist-info/METADATA
MrCalclator-0.0.1.dist-info/WHEEL
MrCalclator-0.0.1.dist-info/top_level.txt
MrCalclator-0.0.1.dist-info/RECORD
