Metadata-Version: 2.1
Name: MrCalclator
Version: 0.0.1
Summary: a simple Calculator that add, multipel, subtracte or dividing two numbers
